flex_menu/__init__.py
flex_menu/_version.py
flex_menu/admin.py
flex_menu/apps.py
flex_menu/context_processors.py
flex_menu/default_settings.py
flex_menu/enums.py
flex_menu/managers.py
flex_menu/models.py
flex_menu/tests.py
flex_menu/translation.py
flex_menu/utils.py
flex_menu/migrations/0001_initial.py
flex_menu/migrations/0002_menuitem_label_en_menuitem_label_fa_and_more.py
flex_menu/migrations/__init__.py
flex_menu/templates/flex_menu/icon.html
flex_menu/templates/flex_menu/link.html
flex_menu/templates/flex_menu/navbar.html
flex_menu/templates/flex_menu/navigation_link.html
flex_menu/templates/flex_menu/navigation_menu.html
flex_menu/templates/flex_menu/sidebar.html
flex_menu/templatetags/__init__.py
flex_menu/templatetags/menu_tags.py
django_flex_menu-0.3.8.dist-info/LICENSE
django_flex_menu-0.3.8.dist-info/METADATA
django_flex_menu-0.3.8.dist-info/WHEEL
django_flex_menu-0.3.8.dist-info/top_level.txt
django_flex_menu-0.3.8.dist-info/RECORD
