Metadata-Version: 2.1
Name: django-flex-menu
Version: 0.3.8
Summary: A server-side menu for django.
Author-email: Saman Zand Haghighi <samanzandh@gmail.com>
License: MIT
Project-URL: Homepage, http://github.com/saman-zand-h/django-flex-menu
Classifier: Development Status :: 3 - Alpha
Classifier: Environment :: Web Environment
Classifier: Framework :: Django
Classifier: Intended Audience :: Developers
Classifier: License :: OSI Approved :: MIT License
Classifier: Operating System :: OS Independent
Classifier: Framework :: Django
Classifier: Framework :: Django :: 3.2
Classifier: Framework :: Django :: 4.0
Classifier: Framework :: Django :: 4.1
Classifier: Programming Language :: Python
Classifier: Programming Language :: Python :: 3
Classifier: Programming Language :: Python :: 3 :: Only
Classifier: Programming Language :: Python :: 3.8
Classifier: Programming Language :: Python :: 3.9
Classifier: Programming Language :: Python :: 3.10
Classifier: Programming Language :: Python :: 3.11
Classifier: Topic :: Software Development :: Libraries :: Python Modules
Requires-Python: >=3.8
License-File: LICENSE
Requires-Dist: django >=3.2
Requires-Dist: django-mptt >=0.14.0
Requires-Dist: django-modeltranslation ~=0.18.11
